celery_typed/__init__.py
celery_typed/codecs.py
celery_typed/py.typed
celery_typed/registry.py
celery_typed-0.2.0.dist-info/METADATA
celery_typed-0.2.0.dist-info/WHEEL
celery_typed-0.2.0.dist-info/licenses/LICENSE
celery_typed-0.2.0.dist-info/RECORD
