Metadata-Version: 2.4
Name: celery-typed
Version: 0.2.0
Summary: Type-safe Pydantic serialization for Celery tasks
Project-URL: Homepage, https://github.com/nwcell/celery-typed
Project-URL: Repository, https://github.com/nwcell/celery-typed
Project-URL: Issues, https://github.com/nwcell/celery-typed/issues
Author-email: Travis Antone <travis.antone@gmail.com>
License: MIT
License-File: LICENSE
Keywords: async,celery,pydantic,serialization,task-queue,type-safe
Classifier: Development Status :: 4 - Beta
Classifier: Intended Audience :: Developers
Classifier: License :: OSI Approved :: MIT License
Classifier: Operating System :: OS Independent
Classifier: Programming Language :: Python :: 3
Classifier: Programming Language :: Python :: 3.10
Classifier: Programming Language :: Python :: 3.11
Classifier: Programming Language :: Python :: 3.12
Classifier: Programming Language :: Python :: 3.13
Classifier: Topic :: Software Development :: Libraries :: Python Modules
Classifier: Topic :: System :: Distributed Computing
Classifier: Typing :: Typed
Requires-Python: >=3.10
Requires-Dist: celery>=5.2.0
Requires-Dist: kombu>=5.2.0
Requires-Dist: pydantic>=2.0.0
Provides-Extra: dev
Requires-Dist: mypy>=1.0.0; extra == 'dev'
Requires-Dist: pytest-cov>=4.0.0; extra == 'dev'
Requires-Dist: pytest>=7.0.0; extra == 'dev'
Requires-Dist: ruff>=0.1.0; extra == 'dev'
